dict2xml/__init__.py
dict2xml/logic.py
dict2xml/version.py
dict2xml-1.7.7.dist-info/METADATA
dict2xml-1.7.7.dist-info/WHEEL
dict2xml-1.7.7.dist-info/licenses/LICENSE
dict2xml-1.7.7.dist-info/RECORD
