Metadata-Version: 2.4
Name: dict2xml
Version: 1.7.7
Summary: Small utility to convert a python dictionary into an XML string
Project-URL: Homepage, http://github.com/delfick/python-dict2xml
Author-email: Stephen Moore <stephen@delfick.com>
License-Expression: MIT
License-File: LICENSE
Classifier: Development Status :: 5 - Production/Stable
Classifier: License :: OSI Approved :: MIT License
Classifier: Operating System :: OS Independent
Classifier: Programming Language :: Python
Classifier: Programming Language :: Python :: 3
Classifier: Topic :: Software Development :: Libraries :: Python Modules
Classifier: Topic :: Text Processing :: Markup :: XML
Requires-Python: >=3.5
Provides-Extra: tests
Requires-Dist: pytest==8.3.2; extra == 'tests'
